pyc3l_cli/__init__.py
pyc3l_cli/cli.py
pyc3l_cli/common.py
pyc3l_cli/cmd/__init__.py
pyc3l_cli/cmd/account.py
pyc3l_cli/cmd/batch_pledge.py
pyc3l_cli/cmd/batch_pledge_simple.py
pyc3l_cli/cmd/batch_transfer.py
pyc3l_cli/cmd/block.py
pyc3l_cli/cmd/block_rate.py
pyc3l_cli/cmd/delegate.py
pyc3l_cli/cmd/example_delegate.py
pyc3l_cli/cmd/example_pledge.py
pyc3l_cli/cmd/example_transfer.py
pyc3l_cli/cmd/lost_transactions.py
pyc3l_cli/cmd/node.py
pyc3l_cli/cmd/pledge.py
pyc3l_cli/cmd/report.py
pyc3l_cli/cmd/transfer_on_behalf.py
pyc3l_cli/cmd/tx.py
pyc3l_cli-0.6.0.dist-info/METADATA
pyc3l_cli-0.6.0.dist-info/WHEEL
pyc3l_cli-0.6.0.dist-info/entry_points.txt
pyc3l_cli-0.6.0.dist-info/licenses/LICENSE
pyc3l_cli-0.6.0.dist-info/RECORD
