Metadata-Version: 2.4
Name: pyc3l-cli
Version: 0.6.0
Summary: ComChain API client library
Project-URL: Homepage, https://github.com/com-chain/pyc3l-cli
Project-URL: Bug Tracker, https://github.com/com-chain/pyc3l-cli/issues
Author-email: Florian Dubath <florian@dubath.org>
License-File: LICENSE
Classifier: License :: OSI Approved :: MIT License
Classifier: Operating System :: OS Independent
Classifier: Programming Language :: Python :: 3
Requires-Python: >=3.7
Requires-Dist: click
Requires-Dist: pyc3l>=0.6.0
Requires-Dist: pyyaml
Requires-Dist: sact-epoch
